Workbook

Sheet Evidence List
A1: Evidence ID | B1: Evidence Title | C1: Evidence Description | D1: Priority | E1: Evidence Domain | F1: Evidence Category | G1: Assignees | H1: Reviewers | I1: Status | J1: Due Date | K1: Tags | L1: PCI DSS 4.0.1 ROC (Standalone)
A2: 33 | B2: (Sample) Incident tickets | C2: Ticket or relevant documentation that shows that incidents are logged, tracked, and communicated to affected parties, by management until resolved, initially and at least weekly or as required. Include all column headers or fields typically filled with information about the incident. | D2: None | E2: Populations | F2: Incident Response Sample Testing | G2: Customer Team | H2: Coalfire Team | I2: Open | L2: 12.10.1
A3: 201 | B3: (Sample) Configurations validating mobile device patching status | C3: Mobile device patch status demonstrating that the devices received the most up-to-date approved patches. Patches should include operating systems. | D3: None | E3: Populations | F3: Mobile Device Sample Testing | G3: Customer Team | H3: Coalfire Team | I3: Open | L3: 6.3.3
A4: 378 | B4: (Sample) Visitor logs | C4: For facilities, datacenters, and secure areas provide the visitor log that demonstrates logging of visitor access to secure areas. Secure areas means areas which contain, process, store, transmit or otherwise house customer data and protected information based on the sample selection provided or the last 90 days. | D4: None | E4: Populations | F4: Physical Access Sample Testing | G4: Customer Team | H4: Coalfire Team | I4: Open | L4: 9.3.2, 9.3.4
A5: 572 | B5: (Sample) Terminated personnel facility access removal tickets | C5: Termination ticket for terminated personnel should show the date when the individual's access authorization was revoked and the date when physical access was removed. | D5: None | E5: Populations | F5: Terminated Employee Sample Testing | G5: Customer Team | H5: Coalfire Team | I5: Open | L5: 9.3.1.1
A6: 912 | B6: (Sample) Antivirus agent configurations | C6: Configurations implementing central management of antivirus agent configurations. Managed configured settings include: - Scan frequency setting, showing whether scans occur on boot and on a subsequent periodic basis (or indicate continuous as applicable for Crowdstrike, network-based malware detection, etc) - Definition update setting - Types of hosts this is applied to (e.g. if Linux or Mac hosts are excluded, please show this or label as Windows only) - Dashboard or central management configuration showing number of active hosts and the total number of offline hosts - Settings that prohibit users from disabling the agent - Settings to mitigate phishing attacks. - Removable media malware analysis | D6: None | E6: Populations | F6: Servers, Hosts, and Instances Sample Testing | G6: Customer Team | H6: Coalfire Team | I6: Open | L6: 5.2.1, 5.2.3, 5.3.1, 5.3.3, 5.3.4, 5.3.5
A7: 927 | B7: (Sample) Cardholder data access logs | C7: Configurations or supporting records demonstrating access to cardholder data are logged and attributable to individual users. Supporting records may include logs demonstrating user attribution and recorded dates and times of sensitive data access. | D7: None | E7: Populations | F7: Cardholder Data Access | G7: Customer Team | H7: Coalfire Team | I7: Open | L7: 3.5.1, 3.5.1.1
A8: 1091 | B8: (Sample) Configurations enforcing session timeouts or automatic disconnections for mobile devices | C8: Configuration of mobile devices enforced through MDM for session timeout and automatic disconnections. Configuration should align with the company's policy for timeouts for mobile devices. | D8: None | E8: Populations | F8: Mobile Device Sample Testing | G8: Customer Team | H8: Coalfire Team | I8: Open | L8: 8.2.8
A9: 1093 | B9: (Sample) Change tickets relevant to selected mobile device (e.g. laptop, phone) | C9: Supporting record demonstrating the submission, approval, and tracking of changes to applicable mobile devices. | D9: None | E9: Populations | F9: Mobile Device Sample Testing | G9: Customer Team | H9: Coalfire Team | I9: Open | L9: 6.5.1
A10: 1098 | B10: (Sample) Change tickets tracking changes to infrastructure | C10: Change tickets for infrastructure changes, showing documentation of impact, approval, functionality testing, and rollback procedures. | D10: None | E10: Populations | F10: Infrastructure Change Management Sample Testing | G10: Customer Team | H10: Coalfire Team | I10: Open | L10: 1.2.2, 6.5.1
A11: 1103 | B11: (Sample) Current employee security awareness training records | C11: Ensure the security awareness training completion artifact includes the name of the current employee and the date when the training was completed. | D11: None | E11: Populations | F11: Current Employee Sample Testing | G11: Customer Team | H11: Coalfire Team | I11: Open | L11: 12.6.3
A12: 1104 | B12: (Sample) Patch deployment to production systems | C12: Logs from automated patch management solutions or change tickets demonstrating adherence to organizations' patch management policy. | D12: None | E12: Populations | F12: Servers, Hosts, and Instances Sample Testing | G12: Customer Team | H12: Coalfire Team | I12: Open | L12: 6.3.3
A13: 1124 | B13: (Sample) Network traffic flow (inbound and outbound) rules | C13: Traffic flow rules that are in place to enforce controls over inbound and outbound traffic to and from the internet and supporting policies from the component that applies filters to inbound and outbound traffic from firewalls. | D13: None | E13: Populations | F13: Firewall Sample Testing | G13: Customer Team | H13: Coalfire Team | I13: Open | L13: 1.2.1, 1.2.2, 1.2.5, 1.2.6, 1.3.3
... A212: 2611 | B212: (Sample) Deployed POI devices | C212: Documented sample listing of locations and payment capture terminals to ensure that POIs in those location(s) match the records. (ROC| 9.5.1.1.a) | D212: None | E212: Populations | F212: Payment Capture Device Sample Testing | G212: Customer Team | H212: Coalfire Team | I212: Open | L212: 9.5.1.1

Sheet Parsed
A1: =concatenate("Title: ",'Evidence List'!B2,char(10),"Evidence type: ",'Evidence List'!E2,char(10),"Associated PCI DSS requirement: ",'Evidence List'!L2,char(10),"Evidence description: ",'Evidence List'!C2) -> Title: (Sample) Incident tickets Evidence type: Populations Associated PCI DSS requirement: 12.10.1 Evidence description: Ticket or relevant documentation that shows that incidents are logged, tracked, and communicated to affected parties, by management until resolved, initially and at least weekly or as required. Include all column headers or fields typically filled with information about the incident.
A2: =concatenate("Title: ",'Evidence List'!B3,char(10),"Evidence type: ",'Evidence List'!E3,char(10),"Associated PCI DSS requirement: ",'Evidence List'!L3,char(10),"Evidence description: ",'Evidence List'!C3) -> Title: (Sample) Configurations validating mobile device patching status Evidence type: Populations Associated PCI DSS requirement: 6.3.3 Evidence description: Mobile device patch status demonstrating that the devices received the most up-to-date approved patches. Patches should include operating systems.
A3: =concatenate("Title: ",'Evidence List'!B4,char(10),"Evidence type: ",'Evidence List'!E4,char(10),"Associated PCI DSS requirement: ",'Evidence List'!L4,char(10),"Evidence description: ",'Evidence List'!C4) -> Title: (Sample) Visitor logs Evidence type: Populations Associated PCI DSS requirement: 9.3.2, 9.3.4 Evidence description: For facilities, datacenters, and secure areas provide the visitor log that demonstrates logging of visitor access to secure areas. Secure areas means areas which contain, process, store, transmit or otherwise house customer data and protected information based on the sample selection provided or the last 90 days.
A4: =concatenate("Title: ",'Evidence List'!B5,char(10),"Evidence type: ",'Evidence List'!E5,char(10),"Associated PCI DSS requirement: ",'Evidence List'!L5,char(10),"Evidence description: ",'Evidence List'!C5) -> Title: (Sample) Terminated personnel facility access removal tickets Evidence type: Populations Associated PCI DSS requirement: 9.3.1.1 Evidence description: Termination ticket for terminated personnel should show the date when the individual's access authorization was revoked and the date when physical access was removed.
A5: =concatenate("Title: ",'Evidence List'!B6,char(10),"Evidence type: ",'Evidence List'!E6,char(10),"Associated PCI DSS requirement: ",'Evidence List'!L6,char(10),"Evidence description: ",'Evidence List'!C6) -> Title: (Sample) Antivirus agent configurations Evidence type: Populations Associated PCI DSS requirement: 5.2.1, 5.2.3, 5.3.1, 5.3.3, 5.3.4, 5.3.5 Evidence description: Configurations implementing central management of antivirus agent configurations. Managed configured settings include: - Scan frequency setting, showing whether scans occur on boot and on a subsequent periodic basis (or indicate continuous as applicable for Crowdstrike, network-based malware detection, etc) - Definition update setting - Types of hosts this is applied to (e.g. if Linux or Mac hosts are excluded, please show this or label as Windows only) - Dashboard or central management configuration showing number of active hosts and the total number of offline hosts - Settings that prohibit users from disabling the agent - Settings to mitigate phishing attacks. - Removable media malware analysis
A6: =concatenate("Title: ",'Evidence List'!B7,char(10),"Evidence type: ",'Evidence List'!E7,char(10),"Associated PCI DSS requirement: ",'Evidence List'!L7,char(10),"Evidence description: ",'Evidence List'!C7) -> Title: (Sample) Cardholder data access logs Evidence type: Populations Associated PCI DSS requirement: 3.5.1, 3.5.1.1 Evidence description: Configurations or supporting records demonstrating access to cardholder data are logged and attributable to individual users. Supporting records may include logs demonstrating user attribution and recorded dates and times of sensitive data access.
A7: =concatenate("Title: ",'Evidence List'!B8,char(10),"Evidence type: ",'Evidence List'!E8,char(10),"Associated PCI DSS requirement: ",'Evidence List'!L8,char(10),"Evidence description: ",'Evidence List'!C8) -> Title: (Sample) Configurations enforcing session timeouts or automatic disconnections for mobile devices Evidence type: Populations Associated PCI DSS requirement: 8.2.8 Evidence description: Configuration of mobile devices enforced through MDM for session timeout and automatic disconnections. Configuration should align with the company's policy for timeouts for mobile devices.
A8: =concatenate("Title: ",'Evidence List'!B9,char(10),"Evidence type: ",'Evidence List'!E9,char(10),"Associated PCI DSS requirement: ",'Evidence List'!L9,char(10),"Evidence description: ",'Evidence List'!C9) -> Title: (Sample) Change tickets relevant to selected mobile device (e.g. laptop, phone) Evidence type: Populations Associated PCI DSS requirement: 6.5.1 Evidence description: Supporting record demonstrating the submission, approval, and tracking of changes to applicable mobile devices.
A9: =concatenate("Title: ",'Evidence List'!B10,char(10),"Evidence type: ",'Evidence List'!E10,char(10),"Associated PCI DSS requirement: ",'Evidence List'!L10,char(10),"Evidence description: ",'Evidence List'!C10) -> Title: (Sample) Change tickets tracking changes to infrastructure Evidence type: Populations Associated PCI DSS requirement: 1.2.2, 6.5.1 Evidence description: Change tickets for infrastructure changes, showing documentation of impact, approval, functionality testing, and rollback procedures.
A10: =concatenate("Title: ",'Evidence List'!B11,char(10),"Evidence type: ",'Evidence List'!E11,char(10),"Associated PCI DSS requirement: ",'Evidence List'!L11,char(10),"Evidence description: ",'Evidence List'!C11) -> Title: (Sample) Current employee security awareness training records Evidence type: Populations Associated PCI DSS requirement: 12.6.3 Evidence description: Ensure the security awareness training completion artifact includes the name of the current employee and the date when the training was completed.
A11: =concatenate("Title: ",'Evidence List'!B12,char(10),"Evidence type: ",'Evidence List'!E12,char(10),"Associated PCI DSS requirement: ",'Evidence List'!L12,char(10),"Evidence description: ",'Evidence List'!C12) -> Title: (Sample) Patch deployment to production systems Evidence type: Populations Associated PCI DSS requirement: 6.3.3 Evidence description: Logs from automated patch management solutions or change tickets demonstrating adherence to organizations' patch management policy.
A12: =concatenate("Title: ",'Evidence List'!B13,char(10),"Evidence type: ",'Evidence List'!E13,char(10),"Associated PCI DSS requirement: ",'Evidence List'!L13,char(10),"Evidence description: ",'Evidence List'!C13) -> Title: (Sample) Network traffic flow (inbound and outbound) rules Evidence type: Populations Associated PCI DSS requirement: 1.2.1, 1.2.2, 1.2.5, 1.2.6, 1.3.3 Evidence description: Traffic flow rules that are in place to enforce controls over inbound and outbound traffic to and from the internet and supporting policies from the component that applies filters to inbound and outbound traffic from firewalls.
... A211: =concatenate("Title: ",'Evidence List'!B212,char(10),"Evidence type: ",'Evidence List'!E212,char(10),"Associated PCI DSS requirement: ",'Evidence List'!L212,char(10),"Evidence description: ",'Evidence List'!C212) -> Title: (Sample) Deployed POI devices Evidence type: Populations Associated PCI DSS requirement: 9.5.1.1 Evidence description: Documented sample listing of locations and payment capture terminals to ensure that POIs in those location(s) match the records. (ROC| 9.5.1.1.a)
